CHANGELOG.txt
LICENCE.txt
MANIFEST.in
README.txt
setup.py
synd/__init__.py
synderep.egg-info/PKG-INFO
synderep.egg-info/SOURCES.txt
synderep.egg-info/dependency_links.txt
synderep.egg-info/top_level.txt