Metadata-Version: 2.1
Name: synderep
Version: 1.0.0
Summary: stress tester for website
Home-page: 
Author: alfie
Author-email: alfiehart481@gmail.com
Requires-Python: >=3.6
License-File: LICENCE.txt
